unqlite.cpython-39-x86_64-linux-gnu.so
medspacy_test_unqlite-0.9.6.dist-info/METADATA
medspacy_test_unqlite-0.9.6.dist-info/top_level.txt
medspacy_test_unqlite-0.9.6.dist-info/WHEEL
medspacy_test_unqlite-0.9.6.dist-info/RECORD
medspacy_test_unqlite-0.9.6.dist-info/LICENSE
